[{"place_id": 44609155, "licence": "Data \u00a9 OpenStreetMap contributors, ODbL 1.0. https://osm.org/copyright", "osm_type": "node", "osm_id": 3502209235, "boundingbox": ["24.9779295", "24.9879295", "121.5363291", "121.5463291"], "lat": "24.9829295", "lon": "121.5413291", "display_name": "Dapinglin, 190, Beixin Road Section 3, Fuxing Village, Xindian District, Dapinglin, New Taipei, 23143, Taiwan", "class": "railway", "type": "station", "importance": 0.33726917163405395, "icon": "https://nominatim.openstreetmap.org/ui/mapicons//transport_train_station2.p.20.png", "geojson": {"type": "Point", "coordinates": [121.5413291, 24.9829295]}}, {"place_id": 60314703, "licence": "Data \u00a9 OpenStreetMap contributors, ODbL 1.0. https://osm.org/copyright", "osm_type": "node", "osm_id": 5295358401, "boundingbox": ["24.9829308", "24.9830308", "121.541297", "121.541397"], "lat": "24.9829808", "lon": "121.541347", "display_name": "Dapinglin, Minquan Road, Bao'an Village, Xindian District, Dapinglin, New Taipei, 23141, Taiwan", "class": "railway", "type": "stop", "importance": 0.33726917163405395, "geojson": {"type": "Point", "coordinates": [121.541347, 24.9829808]}}, {"place_id": 19759432, "licence": "Data \u00a9 OpenStreetMap contributors, ODbL 1.0. https://osm.org/copyright", "osm_type": "node", "osm_id": 2080206484, "boundingbox": ["24.9829291", "24.9830291", "121.541259", "121.541359"], "lat": "24.9829791", "lon": "121.541309", "display_name": "Dapinglin, Minquan Road, Fuxing Village, Xindian District, Dapinglin, New Taipei, 23141, Taiwan", "class": "railway", "type": "stop", "importance": 0.33726917163405395, "geojson": {"type": "Point", "coordinates": [121.541309, 24.9829791]}}, {"place_id": 25252555, "licence": "Data \u00a9 OpenStreetMap contributors, ODbL 1.0. https://osm.org/copyright", "osm_type": "node", "osm_id": 2561560089, "boundingbox": ["24.9545685", "24.9945685", "121.5214876", "121.5614876"], "lat": "24.9745685", "lon": "121.5414876", "display_name": "Dapinglin, New Taipei, 23149, Taiwan", "class": "place", "type": "village", "importance": 0.275, "icon": "https://nominatim.openstreetmap.org/ui/mapicons//poi_place_village.p.20.png", "geojson": {"type": "Point", "coordinates": [121.5414876, 24.9745685]}}, {"place_id": 50239164, "licence": "Data \u00a9 OpenStreetMap contributors, ODbL 1.0. https://osm.org/copyright", "osm_type": "node", "osm_id": 4157593704, "boundingbox": ["24.595413", "24.635413", "120.895545", "120.935545"], "lat": "24.615413", "lon": "120.915545", "display_name": "Dapinglin, Daping Village, Sanwan, Miaoli County, Taiwan", "class": "place", "type": "hamlet", "importance": 0.25, "icon": "https://nominatim.openstreetmap.org/ui/mapicons//poi_place_village.p.20.png", "geojson": {"type": "Point", "coordinates": [120.915545, 24.615413]}}, {"place_id": 77105569, "licence": "Data \u00a9 OpenStreetMap contributors, ODbL 1.0. https://osm.org/copyright", "osm_type": "node", "osm_id": 7174813360, "boundingbox": ["24.9828634", "24.9829634", "121.5421973", "121.5422973"], "lat": "24.9829134", "lon": "121.5422473", "display_name": "Dapinglin, Minquan Road, Bao'an Village, Xindian District, Dapinglin, New Taipei, 23141, Taiwan", "class": "railway", "type": "stop", "importance": 0.001, "geojson": {"type": "Point", "coordinates": [121.5422473, 24.9829134]}}, {"place_id": 78287607, "licence": "Data \u00a9 OpenStreetMap contributors, ODbL 1.0. https://osm.org/copyright", "osm_type": "node", "osm_id": 7174813361, "boundingbox": ["24.9829006", "24.9830006", "121.5421964", "121.5422964"], "lat": "24.9829506", "lon": "121.5422464", "display_name": "Dapinglin, Minquan Road, Bao'an Village, Xindian District, Dapinglin, New Taipei, 23141, Taiwan", "class": "railway", "type": "stop", "importance": 0.001, "geojson": {"type": "Point", "coordinates": [121.5422464, 24.9829506]}}, {"place_id": 19830305, "licence": "Data \u00a9 OpenStreetMap contributors, ODbL 1.0. https://osm.org/copyright", "osm_type": "node", "osm_id": 2081952943, "boundingbox": ["24.980892", "24.980992", "121.5418224", "121.5419224"], "lat": "24.980942", "lon": "121.5418724", "display_name": "Dapinglin, Beixin Road Section 3, Bao'an Village, Xindian District, Dapinglin, New Taipei, 23141, Taiwan", "class": "highway", "type": "bus_stop", "importance": 0.001, "icon": "https://nominatim.openstreetmap.org/ui/mapicons//transport_bus_stop2.p.20.png", "geojson": {"type": "Point", "coordinates": [121.5418724, 24.980942]}}, {"place_id": 19917072, "licence": "Data \u00a9 OpenStreetMap contributors, ODbL 1.0. https://osm.org/copyright", "osm_type": "node", "osm_id": 2081952947, "boundingbox": ["24.9808975", "24.9809975", "121.5416243", "121.5417243"], "lat": "24.9809475", "lon": "121.5416743", "display_name": "Dapinglin, Beixin Road Section 3, Datong Village, Xindian District, Dapinglin, New Taipei, 23141, Taiwan", "class": "highway", "type": "bus_stop", "importance": 0.001, "icon": "https://nominatim.openstreetmap.org/ui/mapicons//transport_bus_stop2.p.20.png", "geojson": {"type": "Point", "coordinates": [121.5416743, 24.9809475]}}, {"place_id": 47793163, "licence": "Data \u00a9 OpenStreetMap contributors, ODbL 1.0. https://osm.org/copyright", "osm_type": "node", "osm_id": 3891423025, "boundingbox": ["24.9810564", "24.9811564", "121.5417702", "121.5418702"], "lat": "24.9811064", "lon": "121.5418202", "display_name": "Dapinglin, Beixin Road Section 3, Bao'an Village, Xindian District, Dapinglin, New Taipei, 23141, Taiwan", "class": "highway", "type": "bus_stop", "importance": 0.001, "icon": "https://nominatim.openstreetmap.org/ui/mapicons//transport_bus_stop2.p.20.png", "geojson": {"type": "Point", "coordinates": [121.5418202, 24.9811064]}}, {"place_id": 58328883, "licence": "Data \u00a9 OpenStreetMap contributors, ODbL 1.0. https://osm.org/copyright", "osm_type": "node", "osm_id": 5122593970, "boundingbox": ["23.8073334", "23.8074334", "120.884117", "120.884217"], "lat": "23.8073834", "lon": "120.884167", "display_name": "\u5927\u5e73\u6797, \u9802\u5e73\u8def, Xiazhuangzi, Dingkan Village, Shuili Township, Nantou County, 55547, Taiwan", "class": "highway", "type": "bus_stop", "importance": 0.001, "icon": "https://nominatim.openstreetmap.org/ui/mapicons//transport_bus_stop2.p.20.png", "geojson": {"type": "Point", "coordinates": [120.884167, 23.8073834]}}, {"place_id": 59210904, "licence": "Data \u00a9 OpenStreetMap contributors, ODbL 1.0. https://osm.org/copyright", "osm_type": "node", "osm_id": 5122593971, "boundingbox": ["23.8068647", "23.8069647", "120.8840874", "120.8841874"], "lat": "23.8069147", "lon": "120.8841374", "display_name": "\u5927\u5e73\u6797, \u9802\u5e73\u8def, Xiazhuangzi, Dingkan Village, Shuili Township, Nantou County, 55547, Taiwan", "class": "highway", "type": "bus_stop", "importance": 0.001, "icon": "https://nominatim.openstreetmap.org/ui/mapicons//transport_bus_stop2.p.20.png", "geojson": {"type": "Point", "coordinates": [120.8841374, 23.8069147]}}]